aaaaa_future_annotations.pth
future_annotations.py
future_annotations-1.0.0.dist-info/LICENSE
future_annotations-1.0.0.dist-info/METADATA
future_annotations-1.0.0.dist-info/WHEEL
future_annotations-1.0.0.dist-info/entry_points.txt
future_annotations-1.0.0.dist-info/top_level.txt
future_annotations-1.0.0.dist-info/RECORD
